README.md
setup.py
vivarium_smoldyn/__init__.py
vivarium_smoldyn.egg-info/PKG-INFO
vivarium_smoldyn.egg-info/SOURCES.txt
vivarium_smoldyn.egg-info/dependency_links.txt
vivarium_smoldyn.egg-info/entry_points.txt
vivarium_smoldyn.egg-info/requires.txt
vivarium_smoldyn.egg-info/top_level.txt
vivarium_smoldyn/composites/__init__.py
vivarium_smoldyn/experiments/__init__.py
vivarium_smoldyn/processes/__init__.py
vivarium_smoldyn/processes/smoldyn_process.py