Metadata-Version: 2.1
Name: vivarium-smoldyn
Version: 0.0.1
Summary: UNKNOWN
Home-page: https://github.com/vivarium-collective/vivarium-smoldyn
Author: Eran Agmon, Steve Andrews, Ryan Spangler
Author-email: eagmon@stanford.edu, steven.s.andrews@gmail.com, ryan.spangler@gmail.com
License: MIT
Platform: UNKNOWN
